rfpb/__init__.py
rfpb/src/__init__.py
rfpb/src/main.py
RFPX-1.1.5.dist-info/LICENSE.txt
RFPX-1.1.5.dist-info/METADATA
RFPX-1.1.5.dist-info/WHEEL
RFPX-1.1.5.dist-info/top_level.txt
RFPX-1.1.5.dist-info/RECORD
