Metadata-Version: 2.1
Name: RFPX
Version: 1.1.5
Summary: A helping tool
Author: rf123
License: RFPX Software Subscription Agreement
Requires-Python: >=3.9
License-File: LICENSE.txt
Requires-Dist: bson >=0.5.10
Requires-Dist: twine >=4.0.2
Requires-Dist: PyAutoGUI ~=0.9.54
Requires-Dist: pytesseract ~=0.3.10
Requires-Dist: pillow ~=10.2.0
Requires-Dist: selenium ~=4.16.0
